setup.py
PermissionsLogging.egg-info/PKG-INFO
PermissionsLogging.egg-info/SOURCES.txt
PermissionsLogging.egg-info/dependency_links.txt
PermissionsLogging.egg-info/top_level.txt
permissions_logging/__init__.py