Metadata-Version: 1.0
Name: PermissionsLogging
Version: 1.1.1
Summary: Python logging handlers that accept file permissions
Home-page: UNKNOWN
Author: Patrick Michaud
Author-email: pmichaud@uw.edu
License: Apache 2.0
Keywords: logging permissions
Platform: UNKNOWN
